crams_resource_usage/__init__.py
crams_resource_usage/asgi.py
crams_resource_usage/permissions.py
crams_resource_usage/settings.py
crams_resource_usage/urls.py
crams_resource_usage/wsgi.py
crams_resource_usage/compute/__init__.py
crams_resource_usage/compute/admin.py
crams_resource_usage/compute/apps.py
crams_resource_usage/compute/models.py
crams_resource_usage/compute/tests.py
crams_resource_usage/compute/views.py
crams_resource_usage/compute/migrations/__init__.py
crams_resource_usage/migrations/0001_initial.py
crams_resource_usage/migrations/__init__.py
crams_resource_usage/storage/__init__.py
crams_resource_usage/storage/admin.py
crams_resource_usage/storage/apps.py
crams_resource_usage/storage/models.py
crams_resource_usage/storage/tests.py
crams_resource_usage/storage/views.py
crams_resource_usage/storage/migrations/__init__.py
crams_resource_usage-1.0.2.dist-info/METADATA
crams_resource_usage-1.0.2.dist-info/WHEEL
crams_resource_usage-1.0.2.dist-info/top_level.txt
crams_resource_usage-1.0.2.dist-info/RECORD
